AUTHORS.rst
CONTRIBUTING.rst
HISTORY.rst
LICENSE
MANIFEST.in
Makefile
README.rst
TODO.rst
dev-requirements.in
dev-requirements.txt
requirements.in
requirements.txt
setup.cfg
setup.py
tox.ini
docs/Makefile
docs/authors.rst
docs/conf.py
docs/contributing.rst
docs/history.rst
docs/index.rst
docs/installation.rst
docs/make.bat
docs/modules.rst
docs/readme.rst
docs/requirements.txt
docs/usage.rst
docs/yammh3.rst
docs/_build/doctrees/authors.doctree
docs/_build/doctrees/contributing.doctree
docs/_build/doctrees/environment.pickle
docs/_build/doctrees/history.doctree
docs/_build/doctrees/index.doctree
docs/_build/doctrees/installation.doctree
docs/_build/doctrees/modules.doctree
docs/_build/doctrees/readme.doctree
docs/_build/doctrees/usage.doctree
docs/_build/doctrees/yammh3.doctree
docs/_build/singlehtml/.buildinfo
docs/_build/singlehtml/index.html
docs/_build/singlehtml/objects.inv
docs/_build/singlehtml/_static/ajax-loader.gif
docs/_build/singlehtml/_static/basic.css
docs/_build/singlehtml/_static/classic.css
docs/_build/singlehtml/_static/comment-bright.png
docs/_build/singlehtml/_static/comment-close.png
docs/_build/singlehtml/_static/comment.png
docs/_build/singlehtml/_static/default.css
docs/_build/singlehtml/_static/doctools.js
docs/_build/singlehtml/_static/down-pressed.png
docs/_build/singlehtml/_static/down.png
docs/_build/singlehtml/_static/file.png
docs/_build/singlehtml/_static/jquery-1.11.1.js
docs/_build/singlehtml/_static/jquery.js
docs/_build/singlehtml/_static/minus.png
docs/_build/singlehtml/_static/plus.png
docs/_build/singlehtml/_static/pygments.css
docs/_build/singlehtml/_static/searchtools.js
docs/_build/singlehtml/_static/sidebar.js
docs/_build/singlehtml/_static/underscore-1.3.1.js
docs/_build/singlehtml/_static/underscore.js
docs/_build/singlehtml/_static/up-pressed.png
docs/_build/singlehtml/_static/up.png
docs/_build/singlehtml/_static/websupport.js
src/yammh3/__init__.py
src/yammh3/_yammh3.pxd
src/yammh3/_yammh3.pyx
src/yammh3.egg-info/PKG-INFO
src/yammh3.egg-info/SOURCES.txt
src/yammh3.egg-info/dependency_links.txt
src/yammh3.egg-info/not-zip-safe
src/yammh3.egg-info/requires.txt
src/yammh3.egg-info/top_level.txt
