Metadata-Version: 1.1
Name: yammh3
Version: 0.1.2
Summary: Python/Cython Murmurhash3 binding.
Home-page: https://github.com/rolando/yammh3
Author: Rolando Espinoza
Author-email: rolando at rmax.io
License: MIT
Keywords: yammh3
Platform: UNKNOWN
Classifier: Development Status :: 2 - Pre-Alpha
Classifier: Intended Audience :: Developers
Classifier: License :: OSI Approved :: MIT License
Classifier: Natural Language :: English
Classifier: Programming Language :: Python :: 2
Classifier: Programming Language :: Python :: 2.7
Classifier: Programming Language :: Python :: 3
Classifier: Programming Language :: Python :: 3.4
Classifier: Programming Language :: Python :: 3.5
